model_processor.cp310-win_amd64.pyd
fulizascoring-0.2.8.dist-info/METADATA
fulizascoring-0.2.8.dist-info/WHEEL
fulizascoring-0.2.8.dist-info/top_level.txt
fulizascoring-0.2.8.dist-info/RECORD
